media_tagging_langchain/__init__.py
media_tagging_langchain/tagger.py
media_tagging_langchain/tagging_strategies.py
media_tagging_langchain-0.1.0.dist-info/METADATA
media_tagging_langchain-0.1.0.dist-info/WHEEL
media_tagging_langchain-0.1.0.dist-info/entry_points.txt
media_tagging_langchain-0.1.0.dist-info/top_level.txt
media_tagging_langchain-0.1.0.dist-info/RECORD
