Metadata-Version: 2.4
Name: media-tagging-langchain
Version: 0.1.0
Summary: Langchain plugin for media-tagging library
Author-email: Andrei Markin <amarkin@google.com>, Sergei Dorogin <segy@google.com>, "Google Inc. (gTech gPS CSE team)" <no-reply@google.com>
License: Apache 2.0
Classifier: Programming Language :: Python :: 3 :: Only
Classifier: Programming Language :: Python :: 3.10
Classifier: Programming Language :: Python :: 3.11
Classifier: Programming Language :: Python :: 3.12
Classifier: Intended Audience :: Developers
Classifier: Topic :: Software Development :: Libraries :: Python Modules
Classifier: Operating System :: OS Independent
Classifier: License :: OSI Approved :: Apache Software License
Requires-Python: >=3.10
Requires-Dist: media_tagging
Requires-Dist: langchain
Requires-Dist: langchain-core
Requires-Dist: langchain-community
